aiothrift/__init__.py
aiothrift/connection.py
aiothrift/errors.py
aiothrift/log.py
aiothrift/pool.py
aiothrift/processor.py
aiothrift/protocol.py
aiothrift/server.py
aiothrift/util.py
aiothrift-0.2.7.dist-info/LICENSE
aiothrift-0.2.7.dist-info/WHEEL
aiothrift-0.2.7.dist-info/METADATA
aiothrift-0.2.7.dist-info/RECORD
