Metadata-Version: 2.1
Name: aiothrift
Version: 0.2.7
Summary: Async Thrift server and client
Home-page: http://github.com/moonshadow/aiothrift/
License: MIT
Keywords: thrift,thriftpy,asyncio
Author: Ryan Wang
Author-email: hwwangwang@gmail.com
Requires-Python: >=3.7,<4.0
Classifier: Environment :: Web Environment
Classifier: Intended Audience :: Developers
Classifier: License :: OSI Approved :: MIT License
Classifier: Programming Language :: Python
Classifier: Programming Language :: Python :: 3
Classifier: Programming Language :: Python :: 3.10
Classifier: Programming Language :: Python :: 3.7
Classifier: Programming Language :: Python :: 3.8
Classifier: Programming Language :: Python :: 3.9
Classifier: Topic :: Software Development
Classifier: Topic :: Software Development :: Libraries
Requires-Dist: async-timeout (>=3.0.1,<5.0.0)
Requires-Dist: thriftpy2 (>=0.4.9,<0.5.0)
Project-URL: Documentation, https://aiothrift.readthedocs.org/
Project-URL: Repository, http://github.com/moonshadow/aiothrift/
